coolML/__init__.py
coolML/data_processing.py
coolML/model_fitting.py
coolML/models.py
coolML-0.0.8.dist-info/METADATA
coolML-0.0.8.dist-info/WHEEL
coolML-0.0.8.dist-info/top_level.txt
coolML-0.0.8.dist-info/RECORD
