Metadata-Version: 2.1
Name: coolML
Version: 0.0.8
Summary: Cool ML is a machine learning workflow developed to optimize thermionic double-assymmetric barrier heterostructures based on semiconductors
Home-page: https://gitlab.citius.usc.es/modev/coolML
Author: Julian Garcia Fernandez 
Author-email: julian.garcia.fernandez2@usc.es
Classifier: Topic :: Utilities
Classifier: Intended Audience :: Developers
Classifier: Intended Audience :: Information Technology
Classifier: License :: OSI Approved :: GNU General Public License v3 (GPLv3)
Classifier: Operating System :: Unix
Classifier: Programming Language :: Python :: 3
Requires-Python: >=3.6
Requires-Dist: torch
Requires-Dist: pytorch-lightning
Requires-Dist: wandb
Requires-Dist: numpy
Requires-Dist: pandas
Requires-Dist: scikit-learn
Requires-Dist: pathlib
